gadcodegen/__init__.py
gadcodegen/cli.py
gadcodegen/const/__init__.py
gadcodegen/const/extenstions.py
gadcodegen/const/files.py
gadcodegen/const/python.py
gadcodegen/const/regexp.py
gadcodegen/const/symbols.py
gadcodegen/const/syntax.py
gadcodegen/os/__init__.py
gadcodegen/os/files.py
gadcodegen/os/folders.py
gadcodegen/os/http.py
gadcodegen/parsers/__init__.py
gadcodegen/parsers/config.py
gadcodegen/utils/__init__.py
gadcodegen/utils/paths.py
gadcodegen/utils/prints.py
gadcodegen/utils/sorting.py
gadcodegen/utils/toml.py
tests/__init__.py
tests/test_init.py
gadcodegen-0.0.3.dist-info/LICENSE
gadcodegen-0.0.3.dist-info/METADATA
gadcodegen-0.0.3.dist-info/WHEEL
gadcodegen-0.0.3.dist-info/entry_points.txt
gadcodegen-0.0.3.dist-info/top_level.txt
gadcodegen-0.0.3.dist-info/RECORD
