Metadata-Version: 2.1
Name: gadcodegen
Version: 0.0.3
Summary: A fast code generator CLI tool
Home-page: https://github.com/AlexDemure/gadcodegen
Author: Alexander Grishchenko
Author-email: alexanderdemure@gmail.com
Classifier: Programming Language :: Python :: 3
Classifier: License :: OSI Approved :: MIT License
Classifier: Operating System :: OS Independent
Requires-Python: >=3.8
License-File: LICENSE
Requires-Dist: gadify
Requires-Dist: jinja2
Requires-Dist: tomli
Requires-Dist: typer
